{
  "id": "feat/mybatis",
  "title": "静态执行Mybatis",
  "description": "Cool Request支持在不启动SpringBoot程序时，执行Mybatis Mapper方法",
  "source": "@site/docs/feat/mybatis.md",
  "sourceDirName": "feat",
  "slug": "/feat/mybatis",
  "permalink": "/docs/feat/mybatis",
  "draft": false,
  "unlisted": false,
  "tags": [],
  "version": "current",
  "sidebarPosition": 1,
  "frontMatter": {
    "sidebar_position": 1,
    "title": "静态执行Mybatis"
  },
  "sidebar": "tutorialSidebar",
  "previous": {
    "title": "特色功能",
    "permalink": "/docs/category/特色功能"
  },
  "next": {
    "title": "压力测试",
    "permalink": "/docs/feat/stress_test"
  }
}